Metadata-Version: 1.0
Name: smay-ros
Version: 0.0.1
Summary: A ROS manager based on smay
Home-page: https://github.com/xkgeng/smay_ros
Author: Geng Xinkuang
Author-email: UNKNOWN
License: MIT Licence
Keywords: pip,smay,ros,smay_ros
Platform: any
